ragkit/chunking/__init__.py
ragkit/chunking/base.py
ragkit/chunking/recursive.py
ragkit/embedding/__init__.py
ragkit/embedding/base.py
ragkit/embedding/openai.py
ragkit/pipeline/__init__.py
ragkit/pipeline/document_pipeline.py
ragkit/pipeline/document_search.py
ragkit/vectorstore/__init__.py
ragkit/vectorstore/base.py
ragkit/vectorstore/qdrant.py
ragkitx-0.1.5.dist-info/licenses/LICENSE
ragkitx-0.1.5.dist-info/METADATA
ragkitx-0.1.5.dist-info/WHEEL
ragkitx-0.1.5.dist-info/top_level.txt
ragkitx-0.1.5.dist-info/RECORD
