Metadata-Version: 2.4
Name: ragkitx
Version: 0.1.5
Summary: Modular RAG toolkit
Author-email: Jan Kristanto Wibisono <jan.nctu@gmail.com>
License: MIT
Project-URL: Homepage, https://github.com/jannctu/ragkit
Project-URL: Repository, https://github.com/jannctu/ragkit
Project-URL: Bug Tracker, https://github.com/jannctu/ragkit/issues
Requires-Python: >=3.9
License-File: LICENSE
Requires-Dist: pydantic>=2.0
Requires-Dist: python-dotenv>=1.0
Requires-Dist: qdrant-client>=1.6
Requires-Dist: openai>=1.0
Requires-Dist: sentence-transformers>=2.2
Requires-Dist: scikit-learn>=1.5
Requires-Dist: nltk>=3.8
Requires-Dist: tiktoken>=0.5.1
Provides-Extra: test
Requires-Dist: pytest; extra == "test"
Dynamic: license-file
